{ "_id" : { "$oid" : "52b30fd912b46925645e39fb" }, "time_id" : 367, "store_sales" : 706.34, "store_cost" : 280.499, "unit_sales" : 348, "customer_count" : 26, "fact_count" : 117 }
{ "_id" : { "$oid" : "52b30fd912b46925645e39fc" }, "time_id" : 368, "store_sales" : 1304.53, "store_cost" : 525.8396, "unit_sales" : 635, "customer_count" : 46, "fact_count" : 206 }
{ "_id" : { "$oid" : "52b30fd912b46925645e39fd" }, "time_id" : 369, "store_sales" : 1294.12, "store_cost" : 515.2609, "unit_sales" : 589, "customer_count" : 47, "fact_count" : 189 }
{ "_id" : { "$oid" : "52b30fd912b46925645e39fe" }, "time_id" : 370, "store_sales" : 42.87, "store_cost" : 17.6873, "unit_sales" : 20, "customer_count" : 4, "fact_count" : 13 }
{ "_id" : { "$oid" : "52b30fd912b46925645e39ff" }, "time_id" : 371, "store_sales" : 1987.19, "store_cost" : 809.6743, "unit_sales" : 966, "customer_count" : 76, "fact_count" : 310 }
{ "_id" : { "$oid" : "52b30fd912b46925645e3a00" }, "time_id" : 372, "store_sales" : 2162.34, "store_cost" : 864.9502, "unit_sales" : 993, "customer_count" : 72, "fact_count" : 308 }
{ "_id" : { "$oid" : "52b30fd912b46925645e3a01" }, "time_id" : 373, "store_sales" : 2696.61, "store_cost" : 1078.2984, "unit_sales" : 1265, "customer_count" : 102, "fact_count" : 419 }
{ "_id" : { "$oid" : "52b30fd912b46925645e3a02" }, "time_id" : 374, "store_sales" : 69.3, "store_cost" : 25.9894, "unit_sales" : 35, "customer_count" : 6, "fact_count" : 19 }
{ "_id" : { "$oid" : "52b30fd912b46925645e3a03" }, "time_id" : 375, "store_sales" : 1090.65, "store_cost" : 431.3554, "unit_sales" : 525, "customer_count" : 42, "fact_count" : 175 }
{ "_id" : { "$oid" : "52b30fda12b46925645e3a04" }, "time_id" : 376, "store_sales" : 1022.08, "store_cost" : 403.1699, "unit_sales" : 460, "customer_count" : 33, "fact_count" : 156 }
{ "_id" : { "$oid" : "52b30fda12b46925645e3a05" }, "time_id" : 377, "store_sales" : 5550.84, "store_cost" : 2214.3738, "unit_sales" : 2760, "customer_count" : 209, "fact_count" : 897 }
{ "_id" : { "$oid" : "52b30fda12b46925645e3a06" }, "time_id" : 378, "store_sales" : 859.62, "store_cost" : 338.2163, "unit_sales" : 355, "customer_count" : 28, "fact_count" : 115 }
{ "_id" : { "$oid" : "52b30fda12b46925645e3a07" }, "time_id" : 379, "store_sales" : 3527.45, "store_cost" : 1404.4789, "unit_sales" : 1629, "customer_count" : 129, "fact_count" : 529 }
{ "_id" : { "$oid" : "52b30fda12b46925645e3a08" }, "time_id" : 380, "store_sales" : 542.08, "store_cost" : 213.8537, "unit_sales" : 261, "customer_count" : 22, "fact_count" : 84 }
{ "_id" : { "$oid" : "52b30fda12b46925645e3a09" }, "time_id" : 381, "store_sales" : 1084.65, "store_cost" : 443.2269, "unit_sales" : 512, "customer_count" : 36, "fact_count" : 166 }
{ "_id" : { "$oid" : "52b30fda12b46925645e3a0a" }, "time_id" : 382, "store_sales" : 1232.19, "store_cost" : 487.443, "unit_sales" : 585, "customer_count" : 37, "fact_count" : 179 }
{ "_id" : { "$oid" : "52b30fda12b46925645e3a0b" }, "time_id" : 383, "store_sales" : 2538.53, "store_cost" : 1000.8063, "unit_sales" : 1146, "customer_count" : 92, "fact_count" : 365 }
{ "_id" : { "$oid" : "52b30fda12b46925645e3a0c" }, "time_id" : 384, "store_sales" : 856.4400000000001, "store_cost" : 341.9665, "unit_sales" : 420, "customer_count" : 34, "fact_count" : 130 }
{ "_id" : { "$oid" : "52b30fda12b46925645e3a0d" }, "time_id" : 385, "store_sales" : 1445.71, "store_cost" : 578.9351, "unit_sales" : 688, "customer_count" : 53, "fact_count" : 220 }
{ "_id" : { "$oid" : "52b30fda12b46925645e3a0e" }, "time_id" : 386, "store_sales" : 4371.05, "store_cost" : 1744.001, "unit_sales" : 2112, "customer_count" : 161, "fact_count" : 671 }
{ "_id" : { "$oid" : "52b30fda12b46925645e3a0f" }, "time_id" : 387, "store_sales" : 2455.63, "store_cost" : 982.0348, "unit_sales" : 1198, "customer_count" : 89, "fact_count" : 384 }
{ "_id" : { "$oid" : "52b30fda12b46925645e3a10" }, "time_id" : 389, "store_sales" : 1659.27, "store_cost" : 667.4021, "unit_sales" : 798, "customer_count" : 63, "fact_count" : 254 }
{ "_id" : { "$oid" : "52b30fda12b46925645e3a11" }, "time_id" : 390, "store_sales" : 54.01, "store_cost" : 20.8004, "unit_sales" : 28, "customer_count" : 5, "fact_count" : 19 }
{ "_id" : { "$oid" : "52b30fda12b46925645e3a12" }, "time_id" : 391, "store_sales" : 2353.39, "store_cost" : 930.5615, "unit_sales" : 1172, "customer_count" : 94, "fact_count" : 375 }
{ "_id" : { "$oid" : "52b30fda12b46925645e3a13" }, "time_id" : 392, "store_sales" : 1241.59, "store_cost" : 507.4709, "unit_sales" : 593, "customer_count" : 46, "fact_count" : 189 }
{ "_id" : { "$oid" : "52b30fda12b46925645e3a14" }, "time_id" : 393, "store_sales" : 898.95, "store_cost" : 365.3156, "unit_sales" : 422, "customer_count" : 36, "fact_count" : 146 }
{ "_id" : { "$oid" : "52b30fda12b46925645e3a15" }, "time_id" : 394, "store_sales" : 862.8, "store_cost" : 339.8095, "unit_sales" : 382, "customer_count" : 34, "fact_count" : 136 }
{ "_id" : { "$oid" : "52b30fda12b46925645e3a16" }, "time_id" : 395, "store_sales" : 1629.46, "store_cost" : 645.0719, "unit_sales" : 731, "customer_count" : 55, "fact_count" : 263 }
{ "_id" : { "$oid" : "52b30fda12b46925645e3a17" }, "time_id" : 398, "store_sales" : 853.17, "store_cost" : 346.153, "unit_sales" : 404, "customer_count" : 29, "fact_count" : 127 }
{ "_id" : { "$oid" : "52b30fda12b46925645e3a18" }, "time_id" : 399, "store_sales" : 1650.61, "store_cost" : 650.9963, "unit_sales" : 759, "customer_count" : 65, "fact_count" : 251 }
{ "_id" : { "$oid" : "52b30fdb12b46925645e3a19" }, "time_id" : 400, "store_sales" : 3622.67, "store_cost" : 1460.7303, "unit_sales" : 1761, "customer_count" : 131, "fact_count" : 560 }
{ "_id" : { "$oid" : "52b30fdb12b46925645e3a1a" }, "time_id" : 401, "store_sales" : 820.76, "store_cost" : 325.221, "unit_sales" : 410, "customer_count" : 39, "fact_count" : 145 }
{ "_id" : { "$oid" : "52b30fdb12b46925645e3a1b" }, "time_id" : 402, "store_sales" : 2253.99, "store_cost" : 906.4829, "unit_sales" : 1076, "customer_count" : 84, "fact_count" : 345 }
{ "_id" : { "$oid" : "52b30fdb12b46925645e3a1c" }, "time_id" : 404, "store_sales" : 1831.61, "store_cost" : 721.6813, "unit_sales" : 918, "customer_count" : 72, "fact_count" : 297 }
{ "_id" : { "$oid" : "52b30fdb12b46925645e3a1d" }, "time_id" : 405, "store_sales" : 1189.2, "store_cost" : 479.6917, "unit_sales" : 592, "customer_count" : 41, "fact_count" : 195 }
{ "_id" : { "$oid" : "52b30fdb12b46925645e3a1e" }, "time_id" : 407, "store_sales" : 1121.07, "store_cost" : 459.2465, "unit_sales" : 515, "customer_count" : 46, "fact_count" : 174 }
{ "_id" : { "$oid" : "52b30fdb12b46925645e3a1f" }, "time_id" : 408, "store_sales" : 1164.7, "store_cost" : 466.7909, "unit_sales" : 550, "customer_count" : 47, "fact_count" : 187 }
{ "_id" : { "$oid" : "52b30fdb12b46925645e3a20" }, "time_id" : 409, "store_sales" : 4221.91, "store_cost" : 1687.6288, "unit_sales" : 1996, "customer_count" : 151, "fact_count" : 638 }
{ "_id" : { "$oid" : "52b30fdb12b46925645e3a21" }, "time_id" : 410, "store_sales" : 1388.48, "store_cost" : 555.1632, "unit_sales" : 648, "customer_count" : 50, "fact_count" : 207 }
{ "_id" : { "$oid" : "52b30fdb12b46925645e3a22" }, "time_id" : 411, "store_sales" : 2085.01, "store_cost" : 832.4705, "unit_sales" : 990, "customer_count" : 75, "fact_count" : 326 }
{ "_id" : { "$oid" : "52b30fdb12b46925645e3a23" }, "time_id" : 412, "store_sales" : 2781.78, "store_cost" : 1095.162, "unit_sales" : 1307, "customer_count" : 105, "fact_count" : 440 }
{ "_id" : { "$oid" : "52b30fdb12b46925645e3a24" }, "time_id" : 413, "store_sales" : 1880.39, "store_cost" : 762.2109, "unit_sales" : 920, "customer_count" : 72, "fact_count" : 301 }
{ "_id" : { "$oid" : "52b30fdc12b46925645e3a25" }, "time_id" : 414, "store_sales" : 2162.85, "store_cost" : 860.5865, "unit_sales" : 1038, "customer_count" : 85, "fact_count" : 334 }
{ "_id" : { "$oid" : "52b30fdc12b46925645e3a26" }, "time_id" : 415, "store_sales" : 1088.15, "store_cost" : 432.1822, "unit_sales" : 513, "customer_count" : 32, "fact_count" : 164 }
{ "_id" : { "$oid" : "52b30fdc12b46925645e3a27" }, "time_id" : 416, "store_sales" : 3290.46, "store_cost" : 1325.2354, "unit_sales" : 1505, "customer_count" : 112, "fact_count" : 493 }
{ "_id" : { "$oid" : "52b30fdc12b46925645e3a28" }, "time_id" : 417, "store_sales" : 956.26, "store_cost" : 382.2787, "unit_sales" : 444, "customer_count" : 36, "fact_count" : 153 }
{ "_id" : { "$oid" : "52b30fdc12b46925645e3a29" }, "time_id" : 418, "store_sales" : 920.6900000000001, "store_cost" : 365.8673, "unit_sales" : 432, "customer_count" : 33, "fact_count" : 142 }
{ "_id" : { "$oid" : "52b30fdc12b46925645e3a2a" }, "time_id" : 419, "store_sales" : 796.8200000000001, "store_cost" : 324.9096, "unit_sales" : 409, "customer_count" : 31, "fact_count" : 131 }
{ "_id" : { "$oid" : "52b30fdc12b46925645e3a2b" }, "time_id" : 420, "store_sales" : 779.9299999999999, "store_cost" : 306.1596, "unit_sales" : 367, "customer_count" : 31, "fact_count" : 123 }
{ "_id" : { "$oid" : "52b30fdc12b46925645e3a2c" }, "time_id" : 421, "store_sales" : 383.43, "store_cost" : 151.3996, "unit_sales" : 192, "customer_count" : 13, "fact_count" : 60 }
{ "_id" : { "$oid" : "52b30fdc12b46925645e3a2d" }, "time_id" : 422, "store_sales" : 2681.05, "store_cost" : 1063.1113, "unit_sales" : 1225, "customer_count" : 94, "fact_count" : 399 }
{ "_id" : { "$oid" : "52b30fdc12b46925645e3a2e" }, "time_id" : 423, "store_sales" : 2400.06, "store_cost" : 946.2666, "unit_sales" : 1151, "customer_count" : 73, "fact_count" : 373 }
{ "_id" : { "$oid" : "52b30fdc12b46925645e3a2f" }, "time_id" : 424, "store_sales" : 1733.74, "store_cost" : 692.0427, "unit_sales" : 835, "customer_count" : 64, "fact_count" : 279 }
{ "_id" : { "$oid" : "52b30fdc12b46925645e3a30" }, "time_id" : 426, "store_sales" : 1227.19, "store_cost" : 480.292, "unit_sales" : 625, "customer_count" : 42, "fact_count" : 199 }
{ "_id" : { "$oid" : "52b30fdd12b46925645e3a31" }, "time_id" : 427, "store_sales" : 1489.49, "store_cost" : 599.2408, "unit_sales" : 734, "customer_count" : 68, "fact_count" : 245 }
{ "_id" : { "$oid" : "52b30fdd12b46925645e3a32" }, "time_id" : 428, "store_sales" : 2050.63, "store_cost" : 807.5194, "unit_sales" : 992, "customer_count" : 71, "fact_count" : 312 }
{ "_id" : { "$oid" : "52b30fdd12b46925645e3a33" }, "time_id" : 429, "store_sales" : 1445.86, "store_cost" : 577.1949, "unit_sales" : 709, "customer_count" : 55, "fact_count" : 230 }
{ "_id" : { "$oid" : "52b30fdd12b46925645e3a34" }, "time_id" : 430, "store_sales" : 1863.08, "store_cost" : 752.925, "unit_sales" : 925, "customer_count" : 73, "fact_count" : 315 }
{ "_id" : { "$oid" : "52b30fdd12b46925645e3a35" }, "time_id" : 431, "store_sales" : 142.75, "store_cost" : 56.947, "unit_sales" : 65, "customer_count" : 10, "fact_count" : 43 }
{ "_id" : { "$oid" : "52b30fdd12b46925645e3a36" }, "time_id" : 432, "store_sales" : 89.98999999999999, "store_cost" : 35.155, "unit_sales" : 40, "customer_count" : 5, "fact_count" : 21 }
{ "_id" : { "$oid" : "52b30fdd12b46925645e3a37" }, "time_id" : 433, "store_sales" : 693.9400000000001, "store_cost" : 279.5267, "unit_sales" : 335, "customer_count" : 24, "fact_count" : 103 }
{ "_id" : { "$oid" : "52b30fdd12b46925645e3a38" }, "time_id" : 434, "store_sales" : 755.76, "store_cost" : 299.9568, "unit_sales" : 385, "customer_count" : 32, "fact_count" : 125 }
{ "_id" : { "$oid" : "52b30fde12b46925645e3a39" }, "time_id" : 435, "store_sales" : 2256.98, "store_cost" : 898.8477, "unit_sales" : 1064, "customer_count" : 78, "fact_count" : 331 }
{ "_id" : { "$oid" : "52b30fde12b46925645e3a3a" }, "time_id" : 436, "store_sales" : 1062.47, "store_cost" : 414.7749, "unit_sales" : 511, "customer_count" : 43, "fact_count" : 176 }
{ "_id" : { "$oid" : "52b30fde12b46925645e3a3b" }, "time_id" : 437, "store_sales" : 923.6799999999999, "store_cost" : 371.2445, "unit_sales" : 436, "customer_count" : 34, "fact_count" : 139 }
{ "_id" : { "$oid" : "52b30fde12b46925645e3a3c" }, "time_id" : 438, "store_sales" : 3617.96, "store_cost" : 1454.0635, "unit_sales" : 1741, "customer_count" : 134, "fact_count" : 563 }
{ "_id" : { "$oid" : "52b30fde12b46925645e3a3d" }, "time_id" : 439, "store_sales" : 1656.88, "store_cost" : 657.4933, "unit_sales" : 784, "customer_count" : 63, "fact_count" : 264 }
{ "_id" : { "$oid" : "52b30fde12b46925645e3a3e" }, "time_id" : 440, "store_sales" : 2810.22, "store_cost" : 1132.6506, "unit_sales" : 1332, "customer_count" : 92, "fact_count" : 432 }
{ "_id" : { "$oid" : "52b30fde12b46925645e3a3f" }, "time_id" : 441, "store_sales" : 743.24, "store_cost" : 296.1761, "unit_sales" : 363, "customer_count" : 32, "fact_count" : 126 }
{ "_id" : { "$oid" : "52b30fde12b46925645e3a40" }, "time_id" : 442, "store_sales" : 927.99, "store_cost" : 363.2101, "unit_sales" : 434, "customer_count" : 33, "fact_count" : 149 }
{ "_id" : { "$oid" : "52b30fde12b46925645e3a41" }, "time_id" : 443, "store_sales" : 1912.2, "store_cost" : 772.5195, "unit_sales" : 862, "customer_count" : 59, "fact_count" : 271 }
{ "_id" : { "$oid" : "52b30fde12b46925645e3a42" }, "time_id" : 444, "store_sales" : 1384, "store_cost" : 565.6408, "unit_sales" : 682, "customer_count" : 52, "fact_count" : 217 }
{ "_id" : { "$oid" : "52b30fde12b46925645e3a43" }, "time_id" : 445, "store_sales" : 2716.15, "store_cost" : 1073.2272, "unit_sales" : 1255, "customer_count" : 100, "fact_count" : 409 }
{ "_id" : { "$oid" : "52b30fde12b46925645e3a44" }, "time_id" : 446, "store_sales" : 6942.08, "store_cost" : 2775.7878, "unit_sales" : 3219, "customer_count" : 236, "fact_count" : 1044 }
{ "_id" : { "$oid" : "52b30fde12b46925645e3a45" }, "time_id" : 447, "store_sales" : 3538.84, "store_cost" : 1400.2568, "unit_sales" : 1638, "customer_count" : 121, "fact_count" : 525 }
{ "_id" : { "$oid" : "52b30fde12b46925645e3a46" }, "time_id" : 448, "store_sales" : 968.17, "store_cost" : 392.2175, "unit_sales" : 449, "customer_count" : 37, "fact_count" : 137 }
{ "_id" : { "$oid" : "52b30fde12b46925645e3a47" }, "time_id" : 449, "store_sales" : 857.34, "store_cost" : 338.6446, "unit_sales" : 398, "customer_count" : 29, "fact_count" : 127 }
{ "_id" : { "$oid" : "52b30fde12b46925645e3a48" }, "time_id" : 450, "store_sales" : 665.8200000000001, "store_cost" : 265.9507, "unit_sales" : 289, "customer_count" : 26, "fact_count" : 98 }
{ "_id" : { "$oid" : "52b30fde12b46925645e3a49" }, "time_id" : 451, "store_sales" : 438.52, "store_cost" : 175.0114, "unit_sales" : 201, "customer_count" : 16, "fact_count" : 63 }
{ "_id" : { "$oid" : "52b30fde12b46925645e3a4a" }, "time_id" : 452, "store_sales" : 1078.15, "store_cost" : 427.444, "unit_sales" : 492, "customer_count" : 36, "fact_count" : 156 }
{ "_id" : { "$oid" : "52b30fde12b46925645e3a4b" }, "time_id" : 453, "store_sales" : 3466.5, "store_cost" : 1388.236, "unit_sales" : 1641, "customer_count" : 123, "fact_count" : 528 }
{ "_id" : { "$oid" : "52b30fde12b46925645e3a4c" }, "time_id" : 454, "store_sales" : 1612.41, "store_cost" : 640.6469, "unit_sales" : 754, "customer_count" : 64, "fact_count" : 248 }
{ "_id" : { "$oid" : "52b30fde12b46925645e3a4d" }, "time_id" : 455, "store_sales" : 691.58, "store_cost" : 281.2776, "unit_sales" : 351, "customer_count" : 30, "fact_count" : 114 }
{ "_id" : { "$oid" : "52b30fde12b46925645e3a4e" }, "time_id" : 457, "store_sales" : 830.35, "store_cost" : 325.7647, "unit_sales" : 391, "customer_count" : 27, "fact_count" : 126 }
{ "_id" : { "$oid" : "52b30fde12b46925645e3a4f" }, "time_id" : 458, "store_sales" : 937.12, "store_cost" : 378.5169, "unit_sales" : 462, "customer_count" : 35, "fact_count" : 147 }
{ "_id" : { "$oid" : "52b30fdf12b46925645e3a50" }, "time_id" : 459, "store_sales" : 2278.91, "store_cost" : 907.3887, "unit_sales" : 1112, "customer_count" : 78, "fact_count" : 357 }
{ "_id" : { "$oid" : "52b30fdf12b46925645e3a51" }, "time_id" : 460, "store_sales" : 3196.63, "store_cost" : 1280.0457, "unit_sales" : 1528, "customer_count" : 116, "fact_count" : 488 }
{ "_id" : { "$oid" : "52b30fdf12b46925645e3a52" }, "time_id" : 461, "store_sales" : 1599.42, "store_cost" : 636.9633, "unit_sales" : 786, "customer_count" : 59, "fact_count" : 248 }
{ "_id" : { "$oid" : "52b30fdf12b46925645e3a53" }, "time_id" : 462, "store_sales" : 875.1799999999999, "store_cost" : 340.2091, "unit_sales" : 424, "customer_count" : 36, "fact_count" : 147 }
{ "_id" : { "$oid" : "52b30fdf12b46925645e3a54" }, "time_id" : 463, "store_sales" : 1907.32, "store_cost" : 767.3973, "unit_sales" : 920, "customer_count" : 65, "fact_count" : 287 }
{ "_id" : { "$oid" : "52b30fdf12b46925645e3a55" }, "time_id" : 464, "store_sales" : 1074.91, "store_cost" : 423.0094, "unit_sales" : 501, "customer_count" : 43, "fact_count" : 175 }
{ "_id" : { "$oid" : "52b30fdf12b46925645e3a56" }, "time_id" : 465, "store_sales" : 704.9, "store_cost" : 274.8856, "unit_sales" : 341, "customer_count" : 30, "fact_count" : 111 }
{ "_id" : { "$oid" : "52b30fdf12b46925645e3a57" }, "time_id" : 466, "store_sales" : 925.1900000000001, "store_cost" : 375.1776, "unit_sales" : 440, "customer_count" : 35, "fact_count" : 153 }
{ "_id" : { "$oid" : "52b30fdf12b46925645e3a58" }, "time_id" : 468, "store_sales" : 2612.47, "store_cost" : 1029.5989, "unit_sales" : 1213, "customer_count" : 92, "fact_count" : 389 }
{ "_id" : { "$oid" : "52b30fdf12b46925645e3a59" }, "time_id" : 469, "store_sales" : 3011.53, "store_cost" : 1201.096, "unit_sales" : 1375, "customer_count" : 102, "fact_count" : 452 }
{ "_id" : { "$oid" : "52b30fdf12b46925645e3a5a" }, "time_id" : 470, "store_sales" : 3645.95, "store_cost" : 1459.941, "unit_sales" : 1717, "customer_count" : 132, "fact_count" : 554 }
{ "_id" : { "$oid" : "52b30fdf12b46925645e3a5b" }, "time_id" : 471, "store_sales" : 2298.32, "store_cost" : 899.1704999999999, "unit_sales" : 1067, "customer_count" : 82, "fact_count" : 338 }
{ "_id" : { "$oid" : "52b30fdf12b46925645e3a5c" }, "time_id" : 472, "store_sales" : 1841.47, "store_cost" : 736.1931, "unit_sales" : 838, "customer_count" : 65, "fact_count" : 270 }
{ "_id" : { "$oid" : "52b30fdf12b46925645e3a5d" }, "time_id" : 473, "store_sales" : 1119.99, "store_cost" : 450.443, "unit_sales" : 508, "customer_count" : 35, "fact_count" : 156 }
{ "_id" : { "$oid" : "52b30fdf12b46925645e3a5e" }, "time_id" : 474, "store_sales" : 670.96, "store_cost" : 266.6279, "unit_sales" : 336, "customer_count" : 27, "fact_count" : 108 }
{ "_id" : { "$oid" : "52b30fe012b46925645e3a5f" }, "time_id" : 475, "store_sales" : 1772.93, "store_cost" : 711.3427, "unit_sales" : 831, "customer_count" : 71, "fact_count" : 280 }
{ "_id" : { "$oid" : "52b30fe012b46925645e3a60" }, "time_id" : 476, "store_sales" : 1031.28, "store_cost" : 421.2255, "unit_sales" : 467, "customer_count" : 45, "fact_count" : 159 }
{ "_id" : { "$oid" : "52b30fe012b46925645e3a61" }, "time_id" : 477, "store_sales" : 868.08, "store_cost" : 348.5646, "unit_sales" : 402, "customer_count" : 28, "fact_count" : 127 }
{ "_id" : { "$oid" : "52b30fe012b46925645e3a62" }, "time_id" : 478, "store_sales" : 1649.01, "store_cost" : 659.5874, "unit_sales" : 759, "customer_count" : 67, "fact_count" : 244 }
{ "_id" : { "$oid" : "52b30fe012b46925645e3a63" }, "time_id" : 479, "store_sales" : 1293.76, "store_cost" : 511.1567, "unit_sales" : 598, "customer_count" : 53, "fact_count" : 231 }
{ "_id" : { "$oid" : "52b30fe012b46925645e3a64" }, "time_id" : 480, "store_sales" : 1224, "store_cost" : 490.8027, "unit_sales" : 597, "customer_count" : 49, "fact_count" : 199 }
{ "_id" : { "$oid" : "52b30fe012b46925645e3a65" }, "time_id" : 481, "store_sales" : 46.37, "store_cost" : 19.1964, "unit_sales" : 23, "customer_count" : 5, "fact_count" : 20 }
{ "_id" : { "$oid" : "52b30fe012b46925645e3a66" }, "time_id" : 482, "store_sales" : 1943.09, "store_cost" : 785.4319, "unit_sales" : 870, "customer_count" : 56, "fact_count" : 271 }
{ "_id" : { "$oid" : "52b30fe012b46925645e3a67" }, "time_id" : 483, "store_sales" : 2416.7, "store_cost" : 966.8658, "unit_sales" : 1147, "customer_count" : 86, "fact_count" : 366 }
{ "_id" : { "$oid" : "52b30fe012b46925645e3a68" }, "time_id" : 484, "store_sales" : 363.87, "store_cost" : 142.5208, "unit_sales" : 181, "customer_count" : 18, "fact_count" : 73 }
{ "_id" : { "$oid" : "52b30fe012b46925645e3a69" }, "time_id" : 485, "store_sales" : 738.54, "store_cost" : 302.5761, "unit_sales" : 345, "customer_count" : 25, "fact_count" : 114 }
{ "_id" : { "$oid" : "52b30fe012b46925645e3a6a" }, "time_id" : 487, "store_sales" : 1602.6, "store_cost" : 632.6512, "unit_sales" : 763, "customer_count" : 61, "fact_count" : 239 }
{ "_id" : { "$oid" : "52b30fe012b46925645e3a6b" }, "time_id" : 488, "store_sales" : 2471.01, "store_cost" : 998.8139, "unit_sales" : 1207, "customer_count" : 86, "fact_count" : 383 }
{ "_id" : { "$oid" : "52b30fe012b46925645e3a6c" }, "time_id" : 489, "store_sales" : 2453.66, "store_cost" : 981.874, "unit_sales" : 1085, "customer_count" : 79, "fact_count" : 348 }
{ "_id" : { "$oid" : "52b30fe012b46925645e3a6d" }, "time_id" : 490, "store_sales" : 665.35, "store_cost" : 267.2279, "unit_sales" : 308, "customer_count" : 28, "fact_count" : 109 }
{ "_id" : { "$oid" : "52b30fe012b46925645e3a6e" }, "time_id" : 491, "store_sales" : 3021.87, "store_cost" : 1220.0456, "unit_sales" : 1441, "customer_count" : 112, "fact_count" : 459 }
{ "_id" : { "$oid" : "52b30fe012b46925645e3a6f" }, "time_id" : 493, "store_sales" : 943.83, "store_cost" : 376.1818, "unit_sales" : 447, "customer_count" : 32, "fact_count" : 144 }
{ "_id" : { "$oid" : "52b30fe012b46925645e3a70" }, "time_id" : 494, "store_sales" : 1821.45, "store_cost" : 721.9571, "unit_sales" : 850, "customer_count" : 65, "fact_count" : 269 }
{ "_id" : { "$oid" : "52b30fe012b46925645e3a71" }, "time_id" : 495, "store_sales" : 7057.98, "store_cost" : 2829.8097, "unit_sales" : 3342, "customer_count" : 257, "fact_count" : 1091 }
{ "_id" : { "$oid" : "52b30fe012b46925645e3a72" }, "time_id" : 496, "store_sales" : 647.52, "store_cost" : 261.4418, "unit_sales" : 323, "customer_count" : 26, "fact_count" : 103 }
{ "_id" : { "$oid" : "52b30fe012b46925645e3a73" }, "time_id" : 497, "store_sales" : 1190.95, "store_cost" : 469.8639, "unit_sales" : 553, "customer_count" : 43, "fact_count" : 187 }
{ "_id" : { "$oid" : "52b30fe112b46925645e3a74" }, "time_id" : 498, "store_sales" : 97.13, "store_cost" : 39.3323, "unit_sales" : 45, "customer_count" : 5, "fact_count" : 26 }
{ "_id" : { "$oid" : "52b30fe112b46925645e3a75" }, "time_id" : 500, "store_sales" : 2173.51, "store_cost" : 869.0368, "unit_sales" : 1058, "customer_count" : 77, "fact_count" : 343 }
{ "_id" : { "$oid" : "52b30fe112b46925645e3a76" }, "time_id" : 501, "store_sales" : 3045.43, "store_cost" : 1205.6594, "unit_sales" : 1501, "customer_count" : 107, "fact_count" : 481 }
{ "_id" : { "$oid" : "52b30fe112b46925645e3a77" }, "time_id" : 502, "store_sales" : 1111.38, "store_cost" : 441.0879, "unit_sales" : 540, "customer_count" : 39, "fact_count" : 174 }
{ "_id" : { "$oid" : "52b30fe112b46925645e3a78" }, "time_id" : 503, "store_sales" : 2011.14, "store_cost" : 806.7886, "unit_sales" : 961, "customer_count" : 72, "fact_count" : 313 }
{ "_id" : { "$oid" : "52b30fe112b46925645e3a79" }, "time_id" : 504, "store_sales" : 1013.32, "store_cost" : 408.8289, "unit_sales" : 471, "customer_count" : 39, "fact_count" : 168 }
{ "_id" : { "$oid" : "52b30fe112b46925645e3a7a" }, "time_id" : 505, "store_sales" : 1611, "store_cost" : 638.0965, "unit_sales" : 730, "customer_count" : 57, "fact_count" : 229 }
{ "_id" : { "$oid" : "52b30fe112b46925645e3a7b" }, "time_id" : 506, "store_sales" : 43.01, "store_cost" : 17.0644, "unit_sales" : 23, "customer_count" : 4, "fact_count" : 17 }
{ "_id" : { "$oid" : "52b30fe112b46925645e3a7c" }, "time_id" : 507, "store_sales" : 3892.34, "store_cost" : 1557.8841, "unit_sales" : 1827, "customer_count" : 148, "fact_count" : 590 }
{ "_id" : { "$oid" : "52b30fe112b46925645e3a7d" }, "time_id" : 508, "store_sales" : 1674.41, "store_cost" : 661.8266, "unit_sales" : 824, "customer_count" : 65, "fact_count" : 272 }
{ "_id" : { "$oid" : "52b30fe112b46925645e3a7e" }, "time_id" : 509, "store_sales" : 728.9, "store_cost" : 289.6082, "unit_sales" : 335, "customer_count" : 29, "fact_count" : 104 }
{ "_id" : { "$oid" : "52b30fe112b46925645e3a7f" }, "time_id" : 511, "store_sales" : 699.16, "store_cost" : 277.5121, "unit_sales" : 327, "customer_count" : 23, "fact_count" : 105 }
{ "_id" : { "$oid" : "52b30fe112b46925645e3a80" }, "time_id" : 512, "store_sales" : 669.62, "store_cost" : 272.9776, "unit_sales" : 319, "customer_count" : 25, "fact_count" : 98 }
{ "_id" : { "$oid" : "52b30fe112b46925645e3a81" }, "time_id" : 513, "store_sales" : 1013.89, "store_cost" : 404.9524, "unit_sales" : 484, "customer_count" : 34, "fact_count" : 151 }
{ "_id" : { "$oid" : "52b30fe112b46925645e3a82" }, "time_id" : 514, "store_sales" : 235.83, "store_cost" : 96.0989, "unit_sales" : 109, "customer_count" : 15, "fact_count" : 66 }
{ "_id" : { "$oid" : "52b30fe112b46925645e3a83" }, "time_id" : 515, "store_sales" : 2488.68, "store_cost" : 1007.6506, "unit_sales" : 1174, "customer_count" : 89, "fact_count" : 373 }
{ "_id" : { "$oid" : "52b30fe112b46925645e3a84" }, "time_id" : 516, "store_sales" : 71.31999999999999, "store_cost" : 28.2835, "unit_sales" : 34, "customer_count" : 5, "fact_count" : 24 }
{ "_id" : { "$oid" : "52b30fe112b46925645e3a85" }, "time_id" : 518, "store_sales" : 783.05, "store_cost" : 314.9892, "unit_sales" : 379, "customer_count" : 29, "fact_count" : 116 }
{ "_id" : { "$oid" : "52b30fe112b46925645e3a86" }, "time_id" : 519, "store_sales" : 1336.81, "store_cost" : 538.9654, "unit_sales" : 650, "customer_count" : 41, "fact_count" : 209 }
{ "_id" : { "$oid" : "52b30fe112b46925645e3a87" }, "time_id" : 520, "store_sales" : 3354.87, "store_cost" : 1331.8238, "unit_sales" : 1558, "customer_count" : 117, "fact_count" : 509 }
{ "_id" : { "$oid" : "52b30fe212b46925645e3a88" }, "time_id" : 521, "store_sales" : 1819.1, "store_cost" : 734.2933, "unit_sales" : 851, "customer_count" : 57, "fact_count" : 270 }
{ "_id" : { "$oid" : "52b30fe212b46925645e3a89" }, "time_id" : 522, "store_sales" : 1277.84, "store_cost" : 514.9794000000001, "unit_sales" : 627, "customer_count" : 48, "fact_count" : 198 }
{ "_id" : { "$oid" : "52b30fe212b46925645e3a8a" }, "time_id" : 523, "store_sales" : 1230.32, "store_cost" : 482.568, "unit_sales" : 588, "customer_count" : 50, "fact_count" : 203 }
{ "_id" : { "$oid" : "52b30fe212b46925645e3a8b" }, "time_id" : 524, "store_sales" : 1569.85, "store_cost" : 619.7526, "unit_sales" : 777, "customer_count" : 55, "fact_count" : 242 }
{ "_id" : { "$oid" : "52b30fe212b46925645e3a8c" }, "time_id" : 527, "store_sales" : 735.53, "store_cost" : 293.667, "unit_sales" : 322, "customer_count" : 29, "fact_count" : 113 }
{ "_id" : { "$oid" : "52b30fe212b46925645e3a8d" }, "time_id" : 528, "store_sales" : 2019.61, "store_cost" : 801.2847, "unit_sales" : 963, "customer_count" : 65, "fact_count" : 293 }
{ "_id" : { "$oid" : "52b30fe212b46925645e3a8e" }, "time_id" : 529, "store_sales" : 1926.08, "store_cost" : 769.2344000000001, "unit_sales" : 862, "customer_count" : 66, "fact_count" : 284 }
{ "_id" : { "$oid" : "52b30fe212b46925645e3a8f" }, "time_id" : 531, "store_sales" : 1919.98, "store_cost" : 765.9675, "unit_sales" : 948, "customer_count" : 69, "fact_count" : 302 }
{ "_id" : { "$oid" : "52b30fe212b46925645e3a90" }, "time_id" : 532, "store_sales" : 2698.5, "store_cost" : 1063.7688, "unit_sales" : 1282, "customer_count" : 93, "fact_count" : 400 }
{ "_id" : { "$oid" : "52b30fe212b46925645e3a91" }, "time_id" : 533, "store_sales" : 2491.64, "store_cost" : 984.7625, "unit_sales" : 1195, "customer_count" : 86, "fact_count" : 379 }
{ "_id" : { "$oid" : "52b30fe212b46925645e3a92" }, "time_id" : 534, "store_sales" : 2120.89, "store_cost" : 847.8202, "unit_sales" : 1000, "customer_count" : 77, "fact_count" : 325 }
{ "_id" : { "$oid" : "52b30fe212b46925645e3a93" }, "time_id" : 535, "store_sales" : 2642.68, "store_cost" : 1061.2743, "unit_sales" : 1244, "customer_count" : 89, "fact_count" : 391 }
{ "_id" : { "$oid" : "52b30fe212b46925645e3a94" }, "time_id" : 536, "store_sales" : 1158.77, "store_cost" : 462.7638, "unit_sales" : 555, "customer_count" : 44, "fact_count" : 175 }
{ "_id" : { "$oid" : "52b30fe212b46925645e3a95" }, "time_id" : 537, "store_sales" : 1629.21, "store_cost" : 650.2451, "unit_sales" : 791, "customer_count" : 64, "fact_count" : 255 }
{ "_id" : { "$oid" : "52b30fe212b46925645e3a96" }, "time_id" : 538, "store_sales" : 3640.84, "store_cost" : 1459.9938, "unit_sales" : 1665, "customer_count" : 130, "fact_count" : 558 }
{ "_id" : { "$oid" : "52b30fe212b46925645e3a97" }, "time_id" : 539, "store_sales" : 3893.04, "store_cost" : 1549.0318, "unit_sales" : 1829, "customer_count" : 139, "fact_count" : 592 }
{ "_id" : { "$oid" : "52b30fe212b46925645e3a98" }, "time_id" : 540, "store_sales" : 2477.7, "store_cost" : 997.3312, "unit_sales" : 1145, "customer_count" : 91, "fact_count" : 365 }
{ "_id" : { "$oid" : "52b30fe212b46925645e3a99" }, "time_id" : 541, "store_sales" : 117.61, "store_cost" : 47.8869, "unit_sales" : 50, "customer_count" : 6, "fact_count" : 31 }
{ "_id" : { "$oid" : "52b30fe212b46925645e3a9a" }, "time_id" : 544, "store_sales" : 2227.99, "store_cost" : 878.5884, "unit_sales" : 1006, "customer_count" : 64, "fact_count" : 331 }
{ "_id" : { "$oid" : "52b30fe212b46925645e3a9b" }, "time_id" : 545, "store_sales" : 1104.92, "store_cost" : 442.5877, "unit_sales" : 517, "customer_count" : 43, "fact_count" : 170 }
{ "_id" : { "$oid" : "52b30fe212b46925645e3a9c" }, "time_id" : 546, "store_sales" : 755.11, "store_cost" : 303.5638, "unit_sales" : 363, "customer_count" : 33, "fact_count" : 128 }
{ "_id" : { "$oid" : "52b30fe212b46925645e3a9d" }, "time_id" : 547, "store_sales" : 399.79, "store_cost" : 152.8262, "unit_sales" : 183, "customer_count" : 19, "fact_count" : 73 }
{ "_id" : { "$oid" : "52b30fe212b46925645e3a9e" }, "time_id" : 548, "store_sales" : 1559.47, "store_cost" : 630.0928, "unit_sales" : 729, "customer_count" : 61, "fact_count" : 239 }
{ "_id" : { "$oid" : "52b30fe312b46925645e3a9f" }, "time_id" : 549, "store_sales" : 2309.58, "store_cost" : 928.2558, "unit_sales" : 1087, "customer_count" : 89, "fact_count" : 361 }
{ "_id" : { "$oid" : "52b30fe312b46925645e3aa0" }, "time_id" : 550, "store_sales" : 1523.77, "store_cost" : 606.6728000000001, "unit_sales" : 751, "customer_count" : 59, "fact_count" : 247 }
{ "_id" : { "$oid" : "52b30fe312b46925645e3aa1" }, "time_id" : 551, "store_sales" : 3147.48, "store_cost" : 1262.4508, "unit_sales" : 1464, "customer_count" : 113, "fact_count" : 480 }
{ "_id" : { "$oid" : "52b30fe312b46925645e3aa2" }, "time_id" : 552, "store_sales" : 2713.38, "store_cost" : 1094.4896, "unit_sales" : 1287, "customer_count" : 94, "fact_count" : 404 }
{ "_id" : { "$oid" : "52b30fe312b46925645e3aa3" }, "time_id" : 553, "store_sales" : 5761.83, "store_cost" : 2273.5948, "unit_sales" : 2745, "customer_count" : 218, "fact_count" : 895 }
{ "_id" : { "$oid" : "52b30fe312b46925645e3aa4" }, "time_id" : 556, "store_sales" : 774.6, "store_cost" : 300.578, "unit_sales" : 367, "customer_count" : 32, "fact_count" : 115 }
{ "_id" : { "$oid" : "52b30fe312b46925645e3aa5" }, "time_id" : 557, "store_sales" : 1309.99, "store_cost" : 518.9397, "unit_sales" : 605, "customer_count" : 50, "fact_count" : 198 }
{ "_id" : { "$oid" : "52b30fe312b46925645e3aa6" }, "time_id" : 558, "store_sales" : 1973.18, "store_cost" : 788.7441, "unit_sales" : 950, "customer_count" : 78, "fact_count" : 301 }
{ "_id" : { "$oid" : "52b30fe312b46925645e3aa7" }, "time_id" : 559, "store_sales" : 1191.12, "store_cost" : 477.1874, "unit_sales" : 550, "customer_count" : 47, "fact_count" : 182 }
{ "_id" : { "$oid" : "52b30fe312b46925645e3aa8" }, "time_id" : 560, "store_sales" : 69.5, "store_cost" : 25.9463, "unit_sales" : 29, "customer_count" : 5, "fact_count" : 20 }
{ "_id" : { "$oid" : "52b30fe312b46925645e3aa9" }, "time_id" : 561, "store_sales" : 2481.09, "store_cost" : 976.2057, "unit_sales" : 1215, "customer_count" : 96, "fact_count" : 397 }
{ "_id" : { "$oid" : "52b30fe312b46925645e3aaa" }, "time_id" : 562, "store_sales" : 80.06, "store_cost" : 31.2838, "unit_sales" : 34, "customer_count" : 5, "fact_count" : 23 }
{ "_id" : { "$oid" : "52b30fe312b46925645e3aab" }, "time_id" : 563, "store_sales" : 1025.85, "store_cost" : 409.8759, "unit_sales" : 515, "customer_count" : 40, "fact_count" : 191 }
{ "_id" : { "$oid" : "52b30fe312b46925645e3aac" }, "time_id" : 564, "store_sales" : 1724.91, "store_cost" : 685.2098999999999, "unit_sales" : 747, "customer_count" : 58, "fact_count" : 245 }
{ "_id" : { "$oid" : "52b30fe312b46925645e3aad" }, "time_id" : 567, "store_sales" : 3427.41, "store_cost" : 1359.0026, "unit_sales" : 1592, "customer_count" : 117, "fact_count" : 516 }
{ "_id" : { "$oid" : "52b30fe312b46925645e3aae" }, "time_id" : 569, "store_sales" : 815.8099999999999, "store_cost" : 326.8994, "unit_sales" : 367, "customer_count" : 28, "fact_count" : 118 }
{ "_id" : { "$oid" : "52b30fe312b46925645e3aaf" }, "time_id" : 570, "store_sales" : 3808.06, "store_cost" : 1516.4996, "unit_sales" : 1771, "customer_count" : 133, "fact_count" : 555 }
{ "_id" : { "$oid" : "52b30fe312b46925645e3ab0" }, "time_id" : 571, "store_sales" : 1781.73, "store_cost" : 705.7216, "unit_sales" : 828, "customer_count" : 62, "fact_count" : 271 }
{ "_id" : { "$oid" : "52b30fe312b46925645e3ab1" }, "time_id" : 573, "store_sales" : 550.55, "store_cost" : 211.8031, "unit_sales" : 268, "customer_count" : 20, "fact_count" : 83 }
{ "_id" : { "$oid" : "52b30fe312b46925645e3ab2" }, "time_id" : 574, "store_sales" : 7959.01, "store_cost" : 3174.9627, "unit_sales" : 3850, "customer_count" : 265, "fact_count" : 1230 }
{ "_id" : { "$oid" : "52b30fe412b46925645e3ab3" }, "time_id" : 575, "store_sales" : 2455.38, "store_cost" : 984.2767, "unit_sales" : 1169, "customer_count" : 93, "fact_count" : 384 }
{ "_id" : { "$oid" : "52b30fe412b46925645e3ab4" }, "time_id" : 576, "store_sales" : 1665.86, "store_cost" : 659.8105, "unit_sales" : 789, "customer_count" : 62, "fact_count" : 268 }
{ "_id" : { "$oid" : "52b30fe412b46925645e3ab5" }, "time_id" : 577, "store_sales" : 137.26, "store_cost" : 57.2874, "unit_sales" : 54, "customer_count" : 5, "fact_count" : 29 }
{ "_id" : { "$oid" : "52b30fe412b46925645e3ab6" }, "time_id" : 579, "store_sales" : 1297.12, "store_cost" : 508.5269, "unit_sales" : 617, "customer_count" : 45, "fact_count" : 195 }
{ "_id" : { "$oid" : "52b30fe412b46925645e3ab7" }, "time_id" : 580, "store_sales" : 1233.97, "store_cost" : 487.5595, "unit_sales" : 597, "customer_count" : 42, "fact_count" : 185 }
{ "_id" : { "$oid" : "52b30fe412b46925645e3ab8" }, "time_id" : 581, "store_sales" : 1008.49, "store_cost" : 401.2062, "unit_sales" : 493, "customer_count" : 33, "fact_count" : 168 }
{ "_id" : { "$oid" : "52b30fe412b46925645e3ab9" }, "time_id" : 582, "store_sales" : 3494.47, "store_cost" : 1395.0621, "unit_sales" : 1663, "customer_count" : 129, "fact_count" : 532 }
{ "_id" : { "$oid" : "52b30fe412b46925645e3aba" }, "time_id" : 583, "store_sales" : 667.92, "store_cost" : 264.9016, "unit_sales" : 303, "customer_count" : 25, "fact_count" : 99 }
{ "_id" : { "$oid" : "52b30fe412b46925645e3abb" }, "time_id" : 584, "store_sales" : 902.86, "store_cost" : 352.9177, "unit_sales" : 457, "customer_count" : 37, "fact_count" : 146 }
{ "_id" : { "$oid" : "52b30fe412b46925645e3abc" }, "time_id" : 585, "store_sales" : 2832.9, "store_cost" : 1139.9798, "unit_sales" : 1358, "customer_count" : 101, "fact_count" : 435 }
{ "_id" : { "$oid" : "52b30fe412b46925645e3abd" }, "time_id" : 586, "store_sales" : 1083.07, "store_cost" : 437.3051, "unit_sales" : 505, "customer_count" : 38, "fact_count" : 163 }
{ "_id" : { "$oid" : "52b30fe412b46925645e3abe" }, "time_id" : 587, "store_sales" : 58.45, "store_cost" : 25.0731, "unit_sales" : 26, "customer_count" : 4, "fact_count" : 14 }
{ "_id" : { "$oid" : "52b30fe412b46925645e3abf" }, "time_id" : 588, "store_sales" : 106.42, "store_cost" : 41.6155, "unit_sales" : 48, "customer_count" : 8, "fact_count" : 30 }
{ "_id" : { "$oid" : "52b30fe412b46925645e3ac0" }, "time_id" : 589, "store_sales" : 1181.84, "store_cost" : 474.1757, "unit_sales" : 569, "customer_count" : 44, "fact_count" : 179 }
{ "_id" : { "$oid" : "52b30fe412b46925645e3ac1" }, "time_id" : 590, "store_sales" : 2598.77, "store_cost" : 1038.115, "unit_sales" : 1222, "customer_count" : 97, "fact_count" : 400 }
{ "_id" : { "$oid" : "52b30fe412b46925645e3ac2" }, "time_id" : 591, "store_sales" : 2672.24, "store_cost" : 1060.8148, "unit_sales" : 1223, "customer_count" : 90, "fact_count" : 388 }
{ "_id" : { "$oid" : "52b30fe412b46925645e3ac3" }, "time_id" : 592, "store_sales" : 2348.79, "store_cost" : 933.249, "unit_sales" : 1077, "customer_count" : 88, "fact_count" : 367 }
{ "_id" : { "$oid" : "52b30fe412b46925645e3ac4" }, "time_id" : 593, "store_sales" : 2593.02, "store_cost" : 1048.9145, "unit_sales" : 1213, "customer_count" : 98, "fact_count" : 391 }
{ "_id" : { "$oid" : "52b30fe412b46925645e3ac5" }, "time_id" : 594, "store_sales" : 1750.6, "store_cost" : 696.559, "unit_sales" : 877, "customer_count" : 65, "fact_count" : 279 }
{ "_id" : { "$oid" : "52b30fe412b46925645e3ac6" }, "time_id" : 595, "store_sales" : 1794.23, "store_cost" : 712.529, "unit_sales" : 878, "customer_count" : 70, "fact_count" : 278 }
{ "_id" : { "$oid" : "52b30fe412b46925645e3ac7" }, "time_id" : 596, "store_sales" : 1870.07, "store_cost" : 754.1518, "unit_sales" : 869, "customer_count" : 63, "fact_count" : 281 }
{ "_id" : { "$oid" : "52b30fe412b46925645e3ac8" }, "time_id" : 597, "store_sales" : 1052.44, "store_cost" : 423.311, "unit_sales" : 487, "customer_count" : 39, "fact_count" : 171 }
{ "_id" : { "$oid" : "52b30fe512b46925645e3ac9" }, "time_id" : 599, "store_sales" : 1165.11, "store_cost" : 459.2063, "unit_sales" : 533, "customer_count" : 47, "fact_count" : 173 }
{ "_id" : { "$oid" : "52b30fe512b46925645e3aca" }, "time_id" : 600, "store_sales" : 2173.75, "store_cost" : 856.4441, "unit_sales" : 1024, "customer_count" : 72, "fact_count" : 317 }
{ "_id" : { "$oid" : "52b30fe512b46925645e3acb" }, "time_id" : 601, "store_sales" : 1733.96, "store_cost" : 697.1674, "unit_sales" : 814, "customer_count" : 67, "fact_count" : 263 }
{ "_id" : { "$oid" : "52b30fe512b46925645e3acc" }, "time_id" : 602, "store_sales" : 2234.59, "store_cost" : 906.591, "unit_sales" : 1021, "customer_count" : 80, "fact_count" : 335 }
{ "_id" : { "$oid" : "52b30fe512b46925645e3acd" }, "time_id" : 603, "store_sales" : 1428.63, "store_cost" : 558.2665, "unit_sales" : 664, "customer_count" : 50, "fact_count" : 220 }
{ "_id" : { "$oid" : "52b30fe512b46925645e3ace" }, "time_id" : 604, "store_sales" : 2130.7, "store_cost" : 844.3575, "unit_sales" : 976, "customer_count" : 78, "fact_count" : 317 }
{ "_id" : { "$oid" : "52b30fe512b46925645e3acf" }, "time_id" : 605, "store_sales" : 1036.13, "store_cost" : 415.7198, "unit_sales" : 485, "customer_count" : 39, "fact_count" : 152 }
{ "_id" : { "$oid" : "52b30fe512b46925645e3ad0" }, "time_id" : 606, "store_sales" : 1911.48, "store_cost" : 761.5165, "unit_sales" : 862, "customer_count" : 65, "fact_count" : 288 }
{ "_id" : { "$oid" : "52b30fe512b46925645e3ad1" }, "time_id" : 607, "store_sales" : 893.12, "store_cost" : 364.854, "unit_sales" : 414, "customer_count" : 29, "fact_count" : 135 }
{ "_id" : { "$oid" : "52b30fe512b46925645e3ad2" }, "time_id" : 608, "store_sales" : 943.9, "store_cost" : 375.8704, "unit_sales" : 422, "customer_count" : 32, "fact_count" : 137 }
{ "_id" : { "$oid" : "52b30fe512b46925645e3ad3" }, "time_id" : 610, "store_sales" : 1295.76, "store_cost" : 514.7777, "unit_sales" : 617, "customer_count" : 42, "fact_count" : 195 }
{ "_id" : { "$oid" : "52b30fe512b46925645e3ad4" }, "time_id" : 611, "store_sales" : 3277.39, "store_cost" : 1296.1148, "unit_sales" : 1541, "customer_count" : 108, "fact_count" : 492 }
{ "_id" : { "$oid" : "52b30fe512b46925645e3ad5" }, "time_id" : 612, "store_sales" : 665.92, "store_cost" : 265.5159, "unit_sales" : 323, "customer_count" : 27, "fact_count" : 102 }
{ "_id" : { "$oid" : "52b30fe512b46925645e3ad6" }, "time_id" : 613, "store_sales" : 1214.99, "store_cost" : 480.5144, "unit_sales" : 570, "customer_count" : 44, "fact_count" : 182 }
{ "_id" : { "$oid" : "52b30fe512b46925645e3ad7" }, "time_id" : 614, "store_sales" : 766.5599999999999, "store_cost" : 300.5532, "unit_sales" : 343, "customer_count" : 28, "fact_count" : 113 }
{ "_id" : { "$oid" : "52b30fe512b46925645e3ad8" }, "time_id" : 615, "store_sales" : 1735.68, "store_cost" : 689.1217, "unit_sales" : 826, "customer_count" : 59, "fact_count" : 263 }
{ "_id" : { "$oid" : "52b30fe512b46925645e3ad9" }, "time_id" : 616, "store_sales" : 1573.36, "store_cost" : 626.8234, "unit_sales" : 736, "customer_count" : 60, "fact_count" : 237 }
{ "_id" : { "$oid" : "52b30fe512b46925645e3ada" }, "time_id" : 617, "store_sales" : 3492.7, "store_cost" : 1390.1353, "unit_sales" : 1595, "customer_count" : 117, "fact_count" : 502 }
{ "_id" : { "$oid" : "52b30fe512b46925645e3adb" }, "time_id" : 618, "store_sales" : 899.4299999999999, "store_cost" : 349.1432, "unit_sales" : 413, "customer_count" : 38, "fact_count" : 151 }
{ "_id" : { "$oid" : "52b30fe512b46925645e3adc" }, "time_id" : 619, "store_sales" : 2965.25, "store_cost" : 1185.7457, "unit_sales" : 1416, "customer_count" : 117, "fact_count" : 479 }
{ "_id" : { "$oid" : "52b30fe512b46925645e3add" }, "time_id" : 620, "store_sales" : 2306.88, "store_cost" : 921.2653, "unit_sales" : 1039, "customer_count" : 69, "fact_count" : 345 }
{ "_id" : { "$oid" : "52b30fe512b46925645e3ade" }, "time_id" : 621, "store_sales" : 1324.33, "store_cost" : 532.8585, "unit_sales" : 602, "customer_count" : 50, "fact_count" : 222 }
{ "_id" : { "$oid" : "52b30fe612b46925645e3adf" }, "time_id" : 622, "store_sales" : 892.88, "store_cost" : 367.0803, "unit_sales" : 411, "customer_count" : 31, "fact_count" : 132 }
{ "_id" : { "$oid" : "52b30fe612b46925645e3ae0" }, "time_id" : 623, "store_sales" : 2036.6, "store_cost" : 823.7472, "unit_sales" : 897, "customer_count" : 68, "fact_count" : 283 }
{ "_id" : { "$oid" : "52b30fe612b46925645e3ae1" }, "time_id" : 624, "store_sales" : 838.98, "store_cost" : 330.6192, "unit_sales" : 397, "customer_count" : 29, "fact_count" : 130 }
{ "_id" : { "$oid" : "52b30fe612b46925645e3ae2" }, "time_id" : 625, "store_sales" : 361.01, "store_cost" : 141.8047, "unit_sales" : 185, "customer_count" : 14, "fact_count" : 62 }
{ "_id" : { "$oid" : "52b30fe612b46925645e3ae3" }, "time_id" : 626, "store_sales" : 1802.9, "store_cost" : 718.4435, "unit_sales" : 855, "customer_count" : 69, "fact_count" : 266 }
{ "_id" : { "$oid" : "52b30fe612b46925645e3ae4" }, "time_id" : 627, "store_sales" : 3119.22, "store_cost" : 1242.391, "unit_sales" : 1418, "customer_count" : 111, "fact_count" : 456 }
{ "_id" : { "$oid" : "52b30fe612b46925645e3ae5" }, "time_id" : 628, "store_sales" : 812.78, "store_cost" : 323.1127, "unit_sales" : 388, "customer_count" : 34, "fact_count" : 140 }
{ "_id" : { "$oid" : "52b30fe612b46925645e3ae6" }, "time_id" : 629, "store_sales" : 2914.11, "store_cost" : 1179.1449, "unit_sales" : 1380, "customer_count" : 111, "fact_count" : 459 }
{ "_id" : { "$oid" : "52b30fe612b46925645e3ae7" }, "time_id" : 630, "store_sales" : 1069.56, "store_cost" : 422.5434, "unit_sales" : 506, "customer_count" : 39, "fact_count" : 160 }
{ "_id" : { "$oid" : "52b30fe612b46925645e3ae8" }, "time_id" : 631, "store_sales" : 1177.19, "store_cost" : 470.2666, "unit_sales" : 574, "customer_count" : 48, "fact_count" : 199 }
{ "_id" : { "$oid" : "52b30fe612b46925645e3ae9" }, "time_id" : 632, "store_sales" : 3585.09, "store_cost" : 1428.6507, "unit_sales" : 1664, "customer_count" : 121, "fact_count" : 536 }
{ "_id" : { "$oid" : "52b30fe612b46925645e3aea" }, "time_id" : 636, "store_sales" : 2737.69, "store_cost" : 1077.4182, "unit_sales" : 1242, "customer_count" : 89, "fact_count" : 389 }
{ "_id" : { "$oid" : "52b30fe612b46925645e3aeb" }, "time_id" : 637, "store_sales" : 159.25, "store_cost" : 65.59950000000001, "unit_sales" : 73, "customer_count" : 10, "fact_count" : 40 }
{ "_id" : { "$oid" : "52b30fe612b46925645e3aec" }, "time_id" : 638, "store_sales" : 800.46, "store_cost" : 319.7266, "unit_sales" : 377, "customer_count" : 28, "fact_count" : 128 }
{ "_id" : { "$oid" : "52b30fe712b46925645e3aed" }, "time_id" : 640, "store_sales" : 93.33, "store_cost" : 36.268, "unit_sales" : 40, "customer_count" : 4, "fact_count" : 19 }
{ "_id" : { "$oid" : "52b30fe712b46925645e3aee" }, "time_id" : 641, "store_sales" : 1639.67, "store_cost" : 656.3067, "unit_sales" : 743, "customer_count" : 66, "fact_count" : 245 }
{ "_id" : { "$oid" : "52b30fe712b46925645e3aef" }, "time_id" : 642, "store_sales" : 826.1900000000001, "store_cost" : 330.1946, "unit_sales" : 399, "customer_count" : 31, "fact_count" : 126 }
{ "_id" : { "$oid" : "52b30fe712b46925645e3af0" }, "time_id" : 643, "store_sales" : 1041.38, "store_cost" : 407.7594, "unit_sales" : 489, "customer_count" : 36, "fact_count" : 153 }
{ "_id" : { "$oid" : "52b30fe712b46925645e3af1" }, "time_id" : 644, "store_sales" : 891.23, "store_cost" : 353.5616, "unit_sales" : 442, "customer_count" : 41, "fact_count" : 152 }
{ "_id" : { "$oid" : "52b30fe712b46925645e3af2" }, "time_id" : 645, "store_sales" : 1223.97, "store_cost" : 500.8661, "unit_sales" : 581, "customer_count" : 39, "fact_count" : 185 }
{ "_id" : { "$oid" : "52b30fe712b46925645e3af3" }, "time_id" : 646, "store_sales" : 2145.18, "store_cost" : 860.1906, "unit_sales" : 1022, "customer_count" : 87, "fact_count" : 348 }
{ "_id" : { "$oid" : "52b30fe712b46925645e3af4" }, "time_id" : 647, "store_sales" : 1258.73, "store_cost" : 488.0011, "unit_sales" : 607, "customer_count" : 45, "fact_count" : 199 }
{ "_id" : { "$oid" : "52b30fe712b46925645e3af5" }, "time_id" : 648, "store_sales" : 952.62, "store_cost" : 379.9484, "unit_sales" : 481, "customer_count" : 38, "fact_count" : 153 }
{ "_id" : { "$oid" : "52b30fe712b46925645e3af6" }, "time_id" : 649, "store_sales" : 2378.1, "store_cost" : 954.3665, "unit_sales" : 1089, "customer_count" : 85, "fact_count" : 359 }
{ "_id" : { "$oid" : "52b30fe712b46925645e3af7" }, "time_id" : 651, "store_sales" : 771.17, "store_cost" : 318.8768, "unit_sales" : 372, "customer_count" : 25, "fact_count" : 120 }
{ "_id" : { "$oid" : "52b30fe712b46925645e3af8" }, "time_id" : 652, "store_sales" : 1814.95, "store_cost" : 733.9598999999999, "unit_sales" : 845, "customer_count" : 68, "fact_count" : 271 }
{ "_id" : { "$oid" : "52b30fe712b46925645e3af9" }, "time_id" : 653, "store_sales" : 1913.07, "store_cost" : 755.3565, "unit_sales" : 937, "customer_count" : 67, "fact_count" : 307 }
{ "_id" : { "$oid" : "52b30fe712b46925645e3afa" }, "time_id" : 654, "store_sales" : 4296.53, "store_cost" : 1707.2808, "unit_sales" : 2043, "customer_count" : 154, "fact_count" : 644 }
{ "_id" : { "$oid" : "52b30fe712b46925645e3afb" }, "time_id" : 655, "store_sales" : 3632.14, "store_cost" : 1440.6477, "unit_sales" : 1671, "customer_count" : 131, "fact_count" : 535 }
{ "_id" : { "$oid" : "52b30fe712b46925645e3afc" }, "time_id" : 656, "store_sales" : 811.74, "store_cost" : 323.7831, "unit_sales" : 374, "customer_count" : 27, "fact_count" : 132 }
{ "_id" : { "$oid" : "52b30fe712b46925645e3afd" }, "time_id" : 657, "store_sales" : 870.96, "store_cost" : 346.0701, "unit_sales" : 426, "customer_count" : 37, "fact_count" : 162 }
{ "_id" : { "$oid" : "52b30fe712b46925645e3afe" }, "time_id" : 658, "store_sales" : 2595.18, "store_cost" : 1046.0867, "unit_sales" : 1206, "customer_count" : 90, "fact_count" : 381 }
{ "_id" : { "$oid" : "52b30fe712b46925645e3aff" }, "time_id" : 659, "store_sales" : 1093.63, "store_cost" : 433.5032, "unit_sales" : 514, "customer_count" : 37, "fact_count" : 170 }
{ "_id" : { "$oid" : "52b30fe712b46925645e3b00" }, "time_id" : 660, "store_sales" : 2342.22, "store_cost" : 936.0635, "unit_sales" : 1069, "customer_count" : 75, "fact_count" : 331 }
{ "_id" : { "$oid" : "52b30fe712b46925645e3b01" }, "time_id" : 661, "store_sales" : 3874.17, "store_cost" : 1542.068, "unit_sales" : 1815, "customer_count" : 138, "fact_count" : 589 }
{ "_id" : { "$oid" : "52b30fe812b46925645e3b02" }, "time_id" : 662, "store_sales" : 1216.68, "store_cost" : 477.1974, "unit_sales" : 588, "customer_count" : 43, "fact_count" : 189 }
{ "_id" : { "$oid" : "52b30fe812b46925645e3b03" }, "time_id" : 663, "store_sales" : 923.7, "store_cost" : 366.7324, "unit_sales" : 443, "customer_count" : 35, "fact_count" : 143 }
{ "_id" : { "$oid" : "52b30fe812b46925645e3b04" }, "time_id" : 665, "store_sales" : 1207.84, "store_cost" : 489.2353, "unit_sales" : 554, "customer_count" : 39, "fact_count" : 174 }
{ "_id" : { "$oid" : "52b30fe812b46925645e3b05" }, "time_id" : 666, "store_sales" : 2460.08, "store_cost" : 989.1821, "unit_sales" : 1176, "customer_count" : 90, "fact_count" : 373 }
{ "_id" : { "$oid" : "52b30fe812b46925645e3b06" }, "time_id" : 669, "store_sales" : 67.81, "store_cost" : 28.4991, "unit_sales" : 32, "customer_count" : 5, "fact_count" : 19 }
{ "_id" : { "$oid" : "52b30fe812b46925645e3b07" }, "time_id" : 671, "store_sales" : 972.2, "store_cost" : 391.2544, "unit_sales" : 474, "customer_count" : 39, "fact_count" : 152 }
{ "_id" : { "$oid" : "52b30fe812b46925645e3b08" }, "time_id" : 672, "store_sales" : 2048.17, "store_cost" : 818.1275000000001, "unit_sales" : 987, "customer_count" : 84, "fact_count" : 305 }
{ "_id" : { "$oid" : "52b30fe812b46925645e3b09" }, "time_id" : 673, "store_sales" : 1430.13, "store_cost" : 569.4109, "unit_sales" : 667, "customer_count" : 48, "fact_count" : 201 }
{ "_id" : { "$oid" : "52b30fe812b46925645e3b0a" }, "time_id" : 674, "store_sales" : 2582.85, "store_cost" : 1037.9581, "unit_sales" : 1209, "customer_count" : 90, "fact_count" : 395 }
{ "_id" : { "$oid" : "52b30fe812b46925645e3b0b" }, "time_id" : 676, "store_sales" : 1360.22, "store_cost" : 539.8543, "unit_sales" : 592, "customer_count" : 49, "fact_count" : 202 }
{ "_id" : { "$oid" : "52b30fe812b46925645e3b0c" }, "time_id" : 677, "store_sales" : 3383.9, "store_cost" : 1355.1916, "unit_sales" : 1563, "customer_count" : 117, "fact_count" : 527 }
{ "_id" : { "$oid" : "52b30fe812b46925645e3b0d" }, "time_id" : 678, "store_sales" : 1948.12, "store_cost" : 775.9717000000001, "unit_sales" : 932, "customer_count" : 76, "fact_count" : 302 }
{ "_id" : { "$oid" : "52b30fe812b46925645e3b0e" }, "time_id" : 679, "store_sales" : 1667.06, "store_cost" : 662.7451, "unit_sales" : 825, "customer_count" : 68, "fact_count" : 283 }
{ "_id" : { "$oid" : "52b30fe812b46925645e3b0f" }, "time_id" : 680, "store_sales" : 2265.23, "store_cost" : 915.225, "unit_sales" : 1068, "customer_count" : 78, "fact_count" : 337 }
{ "_id" : { "$oid" : "52b30fe812b46925645e3b10" }, "time_id" : 681, "store_sales" : 1337.17, "store_cost" : 533.069, "unit_sales" : 599, "customer_count" : 48, "fact_count" : 220 }
{ "_id" : { "$oid" : "52b30fe812b46925645e3b11" }, "time_id" : 683, "store_sales" : 1920.03, "store_cost" : 770.6950000000001, "unit_sales" : 913, "customer_count" : 76, "fact_count" : 296 }
{ "_id" : { "$oid" : "52b30fe812b46925645e3b12" }, "time_id" : 684, "store_sales" : 1177.7, "store_cost" : 465.505, "unit_sales" : 556, "customer_count" : 39, "fact_count" : 177 }
{ "_id" : { "$oid" : "52b30fe812b46925645e3b13" }, "time_id" : 685, "store_sales" : 4039.62, "store_cost" : 1615.967, "unit_sales" : 1932, "customer_count" : 142, "fact_count" : 619 }
{ "_id" : { "$oid" : "52b30fe812b46925645e3b14" }, "time_id" : 686, "store_sales" : 3011.93, "store_cost" : 1199.0944, "unit_sales" : 1432, "customer_count" : 109, "fact_count" : 464 }
{ "_id" : { "$oid" : "52b30fe812b46925645e3b15" }, "time_id" : 687, "store_sales" : 1480.1, "store_cost" : 587.6594, "unit_sales" : 703, "customer_count" : 60, "fact_count" : 235 }
{ "_id" : { "$oid" : "52b30fe812b46925645e3b16" }, "time_id" : 688, "store_sales" : 2376.41, "store_cost" : 957.8989, "unit_sales" : 1098, "customer_count" : 90, "fact_count" : 369 }
{ "_id" : { "$oid" : "52b30fe912b46925645e3b17" }, "time_id" : 689, "store_sales" : 408.05, "store_cost" : 164.1355, "unit_sales" : 207, "customer_count" : 13, "fact_count" : 68 }
{ "_id" : { "$oid" : "52b30fe912b46925645e3b18" }, "time_id" : 690, "store_sales" : 209.92, "store_cost" : 86.0005, "unit_sales" : 102, "customer_count" : 13, "fact_count" : 62 }
{ "_id" : { "$oid" : "52b30fe912b46925645e3b19" }, "time_id" : 691, "store_sales" : 3981.42, "store_cost" : 1610.5931, "unit_sales" : 1892, "customer_count" : 134, "fact_count" : 601 }
{ "_id" : { "$oid" : "52b30fe912b46925645e3b1a" }, "time_id" : 692, "store_sales" : 2885.66, "store_cost" : 1166.8069, "unit_sales" : 1394, "customer_count" : 98, "fact_count" : 454 }
{ "_id" : { "$oid" : "52b30fe912b46925645e3b1b" }, "time_id" : 694, "store_sales" : 1042.24, "store_cost" : 416.8798, "unit_sales" : 487, "customer_count" : 32, "fact_count" : 150 }
{ "_id" : { "$oid" : "52b30fe912b46925645e3b1c" }, "time_id" : 695, "store_sales" : 3378.21, "store_cost" : 1341.1672, "unit_sales" : 1649, "customer_count" : 119, "fact_count" : 536 }
{ "_id" : { "$oid" : "52b30fe912b46925645e3b1d" }, "time_id" : 696, "store_sales" : 2026.26, "store_cost" : 808.4619, "unit_sales" : 950, "customer_count" : 73, "fact_count" : 301 }
{ "_id" : { "$oid" : "52b30fe912b46925645e3b1e" }, "time_id" : 697, "store_sales" : 1793.09, "store_cost" : 703.8768, "unit_sales" : 858, "customer_count" : 70, "fact_count" : 271 }
{ "_id" : { "$oid" : "52b30fe912b46925645e3b1f" }, "time_id" : 698, "store_sales" : 3104.55, "store_cost" : 1241.6754, "unit_sales" : 1456, "customer_count" : 113, "fact_count" : 466 }
{ "_id" : { "$oid" : "52b30fe912b46925645e3b20" }, "time_id" : 699, "store_sales" : 81.31, "store_cost" : 33.0658, "unit_sales" : 38, "customer_count" : 5, "fact_count" : 22 }
{ "_id" : { "$oid" : "52b30fe912b46925645e3b21" }, "time_id" : 700, "store_sales" : 1452.16, "store_cost" : 589.4684, "unit_sales" : 687, "customer_count" : 57, "fact_count" : 217 }
{ "_id" : { "$oid" : "52b30fe912b46925645e3b22" }, "time_id" : 701, "store_sales" : 1165.1, "store_cost" : 468.7773, "unit_sales" : 540, "customer_count" : 40, "fact_count" : 173 }
{ "_id" : { "$oid" : "52b30fe912b46925645e3b23" }, "time_id" : 702, "store_sales" : 1222.6, "store_cost" : 489.3084, "unit_sales" : 580, "customer_count" : 48, "fact_count" : 200 }
{ "_id" : { "$oid" : "52b30fe912b46925645e3b24" }, "time_id" : 703, "store_sales" : 1548.91, "store_cost" : 618.949, "unit_sales" : 715, "customer_count" : 58, "fact_count" : 222 }
{ "_id" : { "$oid" : "52b30fe912b46925645e3b25" }, "time_id" : 704, "store_sales" : 2280.08, "store_cost" : 902.2113000000001, "unit_sales" : 1091, "customer_count" : 92, "fact_count" : 363 }
{ "_id" : { "$oid" : "52b30fe912b46925645e3b26" }, "time_id" : 705, "store_sales" : 2542.49, "store_cost" : 1018.9436, "unit_sales" : 1210, "customer_count" : 90, "fact_count" : 382 }
{ "_id" : { "$oid" : "52b30fe912b46925645e3b27" }, "time_id" : 706, "store_sales" : 973.51, "store_cost" : 388.0395, "unit_sales" : 444, "customer_count" : 38, "fact_count" : 143 }
{ "_id" : { "$oid" : "52b30fea12b46925645e3b28" }, "time_id" : 707, "store_sales" : 2757.57, "store_cost" : 1095.6159, "unit_sales" : 1326, "customer_count" : 97, "fact_count" : 417 }
{ "_id" : { "$oid" : "52b30fea12b46925645e3b29" }, "time_id" : 708, "store_sales" : 934.96, "store_cost" : 380.1373, "unit_sales" : 432, "customer_count" : 25, "fact_count" : 136 }
{ "_id" : { "$oid" : "52b30fea12b46925645e3b2a" }, "time_id" : 709, "store_sales" : 948.8099999999999, "store_cost" : 383.7673, "unit_sales" : 434, "customer_count" : 35, "fact_count" : 140 }
{ "_id" : { "$oid" : "52b30fea12b46925645e3b2b" }, "time_id" : 710, "store_sales" : 978.04, "store_cost" : 380.854, "unit_sales" : 484, "customer_count" : 39, "fact_count" : 156 }
{ "_id" : { "$oid" : "52b30fea12b46925645e3b2c" }, "time_id" : 711, "store_sales" : 5214.2, "store_cost" : 2089.3784, "unit_sales" : 2425, "customer_count" : 176, "fact_count" : 785 }
{ "_id" : { "$oid" : "52b30fea12b46925645e3b2d" }, "time_id" : 713, "store_sales" : 1046.46, "store_cost" : 427.6975, "unit_sales" : 479, "customer_count" : 39, "fact_count" : 158 }
{ "_id" : { "$oid" : "52b30fea12b46925645e3b2e" }, "time_id" : 714, "store_sales" : 1855.7, "store_cost" : 735.8976, "unit_sales" : 906, "customer_count" : 72, "fact_count" : 301 }
{ "_id" : { "$oid" : "52b30fea12b46925645e3b2f" }, "time_id" : 716, "store_sales" : 3201.55, "store_cost" : 1277.1081, "unit_sales" : 1485, "customer_count" : 119, "fact_count" : 478 }
{ "_id" : { "$oid" : "52b30fea12b46925645e3b30" }, "time_id" : 717, "store_sales" : 647.27, "store_cost" : 254.0789, "unit_sales" : 313, "customer_count" : 24, "fact_count" : 117 }
{ "_id" : { "$oid" : "52b30fea12b46925645e3b31" }, "time_id" : 718, "store_sales" : 3257.57, "store_cost" : 1303.3337, "unit_sales" : 1523, "customer_count" : 126, "fact_count" : 515 }
{ "_id" : { "$oid" : "52b30fea12b46925645e3b32" }, "time_id" : 719, "store_sales" : 1053.75, "store_cost" : 421.0934, "unit_sales" : 515, "customer_count" : 44, "fact_count" : 163 }
{ "_id" : { "$oid" : "52b30fea12b46925645e3b33" }, "time_id" : 720, "store_sales" : 3574.29, "store_cost" : 1416.4278, "unit_sales" : 1680, "customer_count" : 137, "fact_count" : 546 }
{ "_id" : { "$oid" : "52b30fea12b46925645e3b34" }, "time_id" : 721, "store_sales" : 3755.82, "store_cost" : 1497.9247, "unit_sales" : 1721, "customer_count" : 127, "fact_count" : 539 }
{ "_id" : { "$oid" : "52b30fea12b46925645e3b35" }, "time_id" : 722, "store_sales" : 3774.42, "store_cost" : 1520.8797, "unit_sales" : 1832, "customer_count" : 137, "fact_count" : 579 }
{ "_id" : { "$oid" : "52b30fea12b46925645e3b36" }, "time_id" : 723, "store_sales" : 909.76, "store_cost" : 357.1031, "unit_sales" : 450, "customer_count" : 34, "fact_count" : 143 }
{ "_id" : { "$oid" : "52b30fea12b46925645e3b37" }, "time_id" : 724, "store_sales" : 1913.73, "store_cost" : 777.7153, "unit_sales" : 874, "customer_count" : 67, "fact_count" : 302 }
{ "_id" : { "$oid" : "52b30fea12b46925645e3b38" }, "time_id" : 725, "store_sales" : 2713.84, "store_cost" : 1083.0545, "unit_sales" : 1247, "customer_count" : 101, "fact_count" : 429 }
{ "_id" : { "$oid" : "52b30fea12b46925645e3b39" }, "time_id" : 726, "store_sales" : 886.25, "store_cost" : 351.5255, "unit_sales" : 420, "customer_count" : 39, "fact_count" : 144 }
{ "_id" : { "$oid" : "52b30fea12b46925645e3b3a" }, "time_id" : 727, "store_sales" : 2454.75, "store_cost" : 978.2205, "unit_sales" : 1156, "customer_count" : 91, "fact_count" : 363 }
{ "_id" : { "$oid" : "52b30fea12b46925645e3b3b" }, "time_id" : 728, "store_sales" : 3179.96, "store_cost" : 1271.5545, "unit_sales" : 1496, "customer_count" : 110, "fact_count" : 480 }
{ "_id" : { "$oid" : "52b30fea12b46925645e3b3c" }, "time_id" : 729, "store_sales" : 2096.92, "store_cost" : 825.443, "unit_sales" : 982, "customer_count" : 77, "fact_count" : 321 }
{ "_id" : { "$oid" : "52b30fea12b46925645e3b3d" }, "time_id" : 730, "store_sales" : 77.33, "store_cost" : 31.0949, "unit_sales" : 36, "customer_count" : 7, "fact_count" : 22 }
